{ 
"wallpapers": 
	[
		{
			"author": "Fayez Ahmed",
			"url": "http://i.imgur.com/d2MnmIl.png",
			"name": "B1"
		},
		{
			"author": "Fayez Ahmed",
			"url": "http://i.imgur.com/vAgJftO.png",
			"name": "B2"
		},
		{
			"author": "Fayez Ahmed",
			"url": "http://i.imgur.com/BqAHxcu.png",
			"name": "A1"
		},
		{
			"author": "Fayez Ahmed",
			"url": "http://i.imgur.com/HFjsyWq.png",
			"name": "A2"
		},
		{
			"author": "Fayez Ahmed",
			"url": "http://i.imgur.com/bwfSjOy.png",
			"name": "A3"
		},
		{
			"author": "Fayez Ahmed",
			"url": "http://i.imgur.com/4spX1cR.png",
			"name": "A4"
		},
		{
			"author": "Fayez Ahmed",
			"url": "http://i.imgur.com/wVMk6Rh.png",
			"name": "A5"
		},
		{
			"author": "Fayez Ahmed",
			"url": "http://i.imgur.com/PptwlIL.png",
			"name": "A6"
		},
		{
			"author": "Fayez Ahmed",
			"url": "http://i.imgur.com/RE0BEHw.png",
			"name": "A7"
		},
		{
			"author": "Fayez Ahmed",
			"url": "http://i.imgur.com/h6kGXJt.png",
			"name": "A8"
		},
		{
			"author": "Fayez Ahmed",
			"url": "http://i.imgur.com/K0SiSPs.png",
			"name": "A9"
		},
		{
			"author": "Fayez Ahmed",
			"url": "http://i.imgur.com/dSCoc0Q.png",
			"name": "A10"
		},
		{
			"author": "Fayez Ahmed",
			"url": "http://i.imgur.com/CKXTmvj.png",
			"name": "A11"
		},
		{
			"author": "Fayez Ahmed",
			"url": "http://i.imgur.com/G3cWy6F.png",
			"name": "A12"
		},
		{
			"author": "Fayez Ahmed",
			"url": "http://i.imgur.com/O3d2O7d.png",
			"name": "A13"
		},
		{
			"author": "Fayez Ahmed",
			"url": "http://i.imgur.com/4WZzPIj.png",
			"name": "A14"
		},
		{
			"author": "Fayez Ahmed",
			"url": "http://i.imgur.com/epDKKNN.png",
			"name": "A15"
		},
		{
			"author": "Fayez Ahmed",
			"url": "http://i.imgur.com/VfOH6E2.png",
			"name": "A16"
		},
		{
			"author": "Fayez Ahmed",
			"url": "http://i.imgur.com/8FSocEo.png",
			"name": "A17"
		},
		{
			"author": "Fayez Ahmed",
			"url": "http://i.imgur.com/2FVncTc.png",
			"name": "A18"
		},
		{
			"author": "Fayez Ahmed",
			"url": "http://i.imgur.com/JDbv6Cj.png",
			"name": "A19"
		},
		{
			"author": "Fayez Ahmed",
			"url": "http://i.imgur.com/IyK6jKH.png",
			"name": "A20"
		},
		{
			"author": "Fayez Ahmed",
			"url": "http://i.imgur.com/W8WtSPh.png",
			"name": "A21"
		},
		{
			"author": "Fayez Ahmed",
			"url": "http://i.imgur.com/I2FPRcZ.png",
			"name": "A22"
		},
		{
			"author": "Fayez Ahmed",
			"url": "http://i.imgur.com/mot7dl4.png",
			"name": "A23"
		},
		{
			"author": "Fayez Ahmed",
			"url": "http://i.imgur.com/UF1WfEI.png",
			"name": "A24"
		},
		{
			"author": "Fayez Ahmed",
			"url": "http://i.imgur.com/4luRUrQ.png",
			"name": "A25"
		},
		{
			"author": "Fayez Ahmed",
			"url": "http://i.imgur.com/DFSIrIn.png",
			"name": "A26"
		},
		{
			"author": "Fayez Ahmed",
			"url": "http://i.imgur.com/irISzKg.png",
			"name": "A27"
		},
		{
			"author": "Fayez Ahmed",
			"url": "http://i.imgur.com/MPvtFQz.png",
			"name": "A28"
		},
		{
			"author": "Fayez Ahmed",
			"url": "http://i.imgur.com/oBJHHBz.png",
			"name": "A29"
		},
		{
			"author": "Fayez Ahmed",
			"url": "http://i.imgur.com/1DtRlsi.png",
			"name": "A30"
		},
		{
			"author": "Fayez Ahmed",
			"url": "http://i.imgur.com/UHwHfs1.png",
			"name": "A31"
		},
		{
			"author": "Fayez Ahmed",
			"url": "http://i.imgur.com/2Fc2A8j.jpg",
			"name": "A32"
		},
		{
			"author": "Fayez Ahmed",
			"url": "http://i.imgur.com/JoPQeVC.jpg",
			"name": "A33"
		},
		{
			"author": "Fayez Ahmed",
			"url": "http://i.imgur.com/88VLhRK.png",
			"name": "A34"
		},
		{
			"author": "Fayez Ahmed",
			"url": "http://i.imgur.com/fXdMB9p.png",
			"name": "A35"
		},
		{
			"author": "Fayez Ahmed",
			"url": "http://i.imgur.com/PzluCe4.png",
			"name": "A36"
		},
		{
			"author": "Fayez Ahmed",
			"url": "http://i.imgur.com/pNg70Tf.png",
			"name": "A37"
		},
		{
			"author": "Fayez Ahmed",
			"url": "http://i.imgur.com/fbEZrQF.png",
			"name": "A38"
		},
		{
			"author": "Fayez Ahmed",
			"url": "http://i.imgur.com/tcqyEK7.png",
			"name": "A39"
		},
		{
			"author": "Fayez Ahmed",
			"url": "http://i.imgur.com/ird98Bo.png",
			"name": "A40"
		},
		{
			"author": "Fayez Ahmed",
			"url": "http://i.imgur.com/4OqQSvy.png",
			"name": "A41"
		},
		{
			"author": "Fayez Ahmed",
			"url": "http://i.imgur.com/kfWai0N.png",
			"name": "A42"
		},
		{
			"author": "Fayez Ahmed",
			"url": "http://i.imgur.com/RXZNgJH.png",
			"name": "A43"
		},
		{
			"author": "Fayez Ahmed",
			"url": "http://i.imgur.com/IdVR2Yd.png",
			"name": "A44"
		},
		{
			"author": "Fayez Ahmed",
			"url": "http://i.imgur.com/9YrsEaw.png",
			"name": "A45"
		},
		{
			"author": "Fayez Ahmed",
			"url": "http://i.imgur.com/5FfdFPg.png",
			"name": "A46"
		},
		{
			"author": "Fayez Ahmed",
			"url": "http://i.imgur.com/2r8fQJJ.png",
			"name": "A47"
		},
		{
			"author": "Fayez Ahmed",
			"url": "http://i.imgur.com/kV8fRtL.png",
			"name": "A48"
		},
		{
			"author": "Fayez Ahmed",
			"url": "http://i.imgur.com/lfIjcCv.png",
			"name": "A49"
		},
		{
			"author": "Fayez Ahmed",
			"url": "http://i.imgur.com/I7aQNXJ.png",
			"name": "A50"
		},
		{
			"author": "Fayez Ahmed",
			"url": "http://i.imgur.com/IoLVjka.png",
			"name": "A51"
		},
		{
			"author": "Fayez Ahmed",
			"url": "http://i.imgur.com/pf98WyO.png",
			"name": "A52"
		},
		{
			"author": "Fayez Ahmed",
			"url": "http://i.imgur.com/cPlmG57.png",
			"name": "A53"
		},
		{
			"author": "Fayez Ahmed",
			"url": "http://i.imgur.com/69G3u1O.png",
			"name": "A54"
		},
		{
			"author": "Fayez Ahmed",
			"url": "http://i.imgur.com/t8OWy5J.png",
			"name": "A55"
		},
		{
			"author": "Fayez Ahmed",
			"url": "http://i.imgur.com/lMKf3QR.png",
			"name": "A56"
		},
		{
			"author": "Fayez Ahmed",
			"url": "http://i.imgur.com/fBOVidq.png",
			"name": "A57"
		},
		{
			"author": "Fayez Ahmed",
			"url": "http://i.imgur.com/RgonkR5.jpg",
			"name": "A58"
		},
		{
			"author": "Fayez Ahmed",
			"url": "http://i.imgur.com/4AaPFzK.png",
			"name": "A59"
		},
		{
			"author": "Fayez Ahmed",
			"url": "http://i.imgur.com/M1figPW.png",
			"name": "A60"
		},
		{
			"author": "Fayez Ahmed",
			"url": "http://i.imgur.com/7talUgb.png",
			"name": "A61"
		},
		{
			"author": "Fayez Ahmed",
			"url": "http://i.imgur.com/uQgepSE.png",
			"name": "A62"
		},
		{
			"author": "Fayez Ahmed",
			"url": "http://i.imgur.com/5ca1B6t.png",
			"name": "A63"
		},
		{
			"author": "Fayez Ahmed",
			"url": "http://i.imgur.com/ESLZqqd.png",
			"name": "A64"
		},
		{
			"author": "Fayez Ahmed",
			"url": "http://i.imgur.com/7QoiNQV.png",
			"name": "A65"
		},
		{
			"author": "Fayez Ahmed",
			"url": "http://i.imgur.com/ZaFGmOQ.png",
			"name": "A66"
		},
		{
			"author": "Fayez Ahmed",
			"url": "http://i.imgur.com/RctsSH2.png",
			"name": "A67"
		},
		{
			"author": "Fayez Ahmed",
			"url": "http://i.imgur.com/E5LhI2Q.png",
			"name": "A68"
		},
		{
			"author": "Fayez Ahmed",
			"url": "http://i.imgur.com/WBlyxZF.png",
			"name": "A69"
		},
		{
			"author": "Fayez Ahmed",
			"url": "http://i.imgur.com/r18OjaX.png",
			"name": "A70"
		},
		{
			"author": "Fayez Ahmed",
			"url": "http://i.imgur.com/u0BgwcK.png",
			"name": "A71"
		},
		{
			"author": "Fayez Ahmed",
			"url": "http://i.imgur.com/k2MOQXq.png",
			"name": "A72"
		},
		{
			"author": "Fayez Ahmed",
			"url": "http://i.imgur.com/0rubkRI.png",
			"name": "A73"
		},
		{
			"author": "Fayez Ahmed",
			"url": "http://i.imgur.com/AhMVksi.png",
			"name": "A74"
		},
		{
			"author": "Fayez Ahmed",
			"url": "http://i.imgur.com/K0OZ8bf.png",
			"name": "A75"
		},
		{
			"author": "Fayez Ahmed",
			"url": "http://i.imgur.com/yKe6bzs.png",
			"name": "A76"
		},
		{
			"author": "Fayez Ahmed",
			"url": "http://i.imgur.com/QFZ1DS5.png",
			"name": "A77"
		},
		{
			"author": "Fayez Ahmed",
			"url": "http://i.imgur.com/tQXGX7Z.png",
			"name": "A78"
		},
		{
			"author": "Fayez Ahmed",
			"url": "http://i.imgur.com/8xq6HDL.png",
			"name": "A79"
		},
		{
			"author": "Fayez Ahmed",
			"url": "http://i.imgur.com/8xq6HDL.png",
			"name": "A80"
		},
		{
			"author": "Fayez Ahmed",
			"url": "http://i.imgur.com/Z7FXioi.png",
			"name": "A81"
		},
		{
			"author": "Fayez Ahmed",
			"url": "http://i.imgur.com/nU14K4u.jpg",
			"name": "A82"
		}
	]
}
